movielens_private_api/__init__.py
movielens_private_api/movielens.py
movielens_private_api-0.0.1.dist-info/LICENSE
movielens_private_api-0.0.1.dist-info/METADATA
movielens_private_api-0.0.1.dist-info/WHEEL
movielens_private_api-0.0.1.dist-info/top_level.txt
movielens_private_api-0.0.1.dist-info/RECORD
