Metadata-Version: 2.1
Name: movielens-private-api
Version: 0.0.1
Summary: A package to interact with Movielens unpublished API
Home-page: https://github.com/Mello-Yello/movielens-api
Author: Giacomo Pigani
Author-email: pigani.giacomo+movielens@gmail.com
License: GPLv3
Platform: UNKNOWN
Classifier: License :: OSI Approved :: GNU General Public License v3 (GPLv3)
Classifier: Programming Language :: Python :: 2.7
Classifier: Programming Language :: Python :: 3
Classifier: Programming Language :: Python :: 3.6
License-File: LICENSE
Requires-Dist: requests
